spheroidal/__init__.py
spheroidal/leaver.py
spheroidal/spectral.py
spheroidal/spherical.py
spheroidal/wrapper.py
spheroidal-0.1.1.dist-info/LICENSE
spheroidal-0.1.1.dist-info/METADATA
spheroidal-0.1.1.dist-info/WHEEL
spheroidal-0.1.1.dist-info/top_level.txt
spheroidal-0.1.1.dist-info/RECORD
